tinyquaternion/__init__.py
tinyquaternion/tinyQuaternion.py
tinyquaternion-0.0.1.dist-info/LICENSE
tinyquaternion-0.0.1.dist-info/METADATA
tinyquaternion-0.0.1.dist-info/WHEEL
tinyquaternion-0.0.1.dist-info/top_level.txt
tinyquaternion-0.0.1.dist-info/RECORD
