Metadata-Version: 2.1
Name: tinyquaternion
Version: 0.0.1
Summary: A Tiny Python Package for Quaternions
Home-page: https://github.com/rezaahmadzadeh/tinyquaternion
Author: Reza Ahmadzadeh
Author-email: reza.ahmadzadeh.iit@gmail.com
License: UNKNOWN
Platform: UNKNOWN
Classifier: Programming Language :: Python :: 3
Classifier: License :: OSI Approved :: MIT License
Classifier: Operating System :: OS Independent
